decoratorbasic.py
decoratorbasic-1.0.1.dist-info/licenses/LICENSE
decoratorbasic-1.0.1.dist-info/METADATA
decoratorbasic-1.0.1.dist-info/WHEEL
decoratorbasic-1.0.1.dist-info/top_level.txt
decoratorbasic-1.0.1.dist-info/RECORD
