Metadata-Version: 2.4
Name: decoratorbasic
Version: 1.0.1
Summary: Simple tools for creating and managing decorators in Python.
Author-email: TahsinCr <TahsinCr@outlook.com>
License: MIT
Project-URL: Homepage, https://github.com/TahsinCr/python-decoratorbasic
Project-URL: Source, https://github.com/TahsinCr/python-decoratorbasic
Keywords: decoratorbasic,decorator,basic,definator,xcollection
Classifier: Typing :: Typed
Classifier: Intended Audience :: Developers
Classifier: Programming Language :: Python :: 3
Classifier: License :: OSI Approved :: MIT License
Classifier: Operating System :: OS Independent
Requires-Python: >=3
License-File: LICENSE
Requires-Dist: callabletype>=1.0
Dynamic: license-file
